{
  "collectionName": "components_dimension_dimensions",
  "info": {
    "displayName": "dimension",
    "icon": "arrowDown",
    "description": ""
  },
  "options": {},
  "attributes": {
    "length": {
      "type": "float"
    },
    "width": {
      "type": "float"
    },
    "height": {
      "type": "float"
    },
    "volume": {
      "type": "float"
    },
    "units": {
      "type": "enumeration",
      "enum": [
        "millimeter_mm",
        "centimeter_cm",
        "meter_m",
        "inch_in",
        "feet_ft"
      ]
    }
  }
}
